snakecdysis/Snakecdysis_logo.png
snakecdysis/__init__.py
snakecdysis/__main__.py
snakecdysis/_version.py
snakecdysis/cli_wrapper.py
snakecdysis/edit_files.py
snakecdysis/global_variable.py
snakecdysis/install.py
snakecdysis/run.py
snakecdysis/snake_wrapper.py
snakecdysis/useful_function.py
snakecdysis/scripts/generate_template.py
snakecdysis/templates/pyproject.toml
snakecdysis/templates/PKGNAME/VERSION
snakecdysis/templates/PKGNAME/__init__.py
snakecdysis/templates/PKGNAME/global_variables.py
snakecdysis/templates/PKGNAME/main.py
snakecdysis/templates/PKGNAME/module.py
snakecdysis/templates/PKGNAME/install_files/cluster_config_SLURM.yaml
snakecdysis/templates/PKGNAME/install_files/config.yaml
snakecdysis/templates/PKGNAME/install_files/tools_path.yaml
snakecdysis/templates/PKGNAME/snakefiles/snakefile
snakecdysis/templates/PKGNAME/snakemake_scripts/report_template/versions.csv
snakecdysis-2.0.1.dist-info/licenses/LICENSE
snakecdysis-2.0.1.dist-info/METADATA
snakecdysis-2.0.1.dist-info/WHEEL
snakecdysis-2.0.1.dist-info/entry_points.txt
snakecdysis-2.0.1.dist-info/top_level.txt
snakecdysis-2.0.1.dist-info/RECORD
