Metadata-Version: 2.4
Name: snakecdysis
Version: 2.0.1
Summary: You want to wrap your best snakemake workflow to be easy install and run, Snakecdysis is for you !!!!! Tha aim of Snakecdysis is to easy-wrapped snakemake workflow as python package and then build sub-commands to manage this. !!!!!
Author-email: "Ravel Sebastien (CIRAD)" <sebastien.ravel@cirad.fr>
License-Expression: MIT
Project-URL: Homepage, https://forge.ird.fr/phim/sravel/snakecdysis
Project-URL: Downloads, https://forge.ird.fr/phim/sravel/snakecdysis/-/releases
Project-URL: Bug Tracker, https://forge.ird.fr/phim/sravel/snakecdysis/issues
Project-URL: Documentation, https://snakecdysis.readthedocs.io/en/latest/
Project-URL: Source Code, https://forge.ird.fr/phim/sravel/snakecdysis
Keywords: snakemake,wrapper,installation,HPC
Classifier: Development Status :: 5 - Production/Stable
Classifier: Intended Audience :: Developers
Classifier: Intended Audience :: End Users/Desktop
Classifier: Natural Language :: English
Classifier: Operating System :: POSIX :: Linux
Classifier: Programming Language :: Python :: 3.11
Classifier: Programming Language :: Python :: 3.12
Classifier: Topic :: Scientific/Engineering
Classifier: Topic :: Scientific/Engineering :: Bio-Informatics
Requires-Python: >=3.11
License-File: LICENSE
Requires-Dist: PyYAML
Requires-Dist: click>=8.0.3
Requires-Dist: cookiecutter
Requires-Dist: docutils
Requires-Dist: python-gitlab
Requires-Dist: snakemake>=8.0.0
Requires-Dist: snakemake-executor-plugin-slurm
Requires-Dist: tqdm
Requires-Dist: pulp<2.8
Requires-Dist: pandas
Provides-Extra: doc
Requires-Dist: sphinx_click; extra == "doc"
Requires-Dist: sphinx_copybutton; extra == "doc"
Requires-Dist: sphinx_rtd_theme; extra == "doc"
Requires-Dist: autodocsumm>=0.1.13; extra == "doc"
Requires-Dist: autodoc>=0.3; extra == "doc"
Requires-Dist: sphinx>=3.1.2; extra == "doc"
Requires-Dist: sphinx_automodapi>=0.12; extra == "doc"
Requires-Dist: sphinxcontrib-napoleon>=0.7; extra == "doc"
Requires-Dist: sphinxcontrib-autoprogram; extra == "doc"
Requires-Dist: snakemake; extra == "doc"
Requires-Dist: sphinx-click; extra == "doc"
Requires-Dist: sphinx_design; extra == "doc"
Requires-Dist: pandas; extra == "doc"
Requires-Dist: toml; extra == "doc"
Dynamic: license-file
